scrapy_poet/VERSION
scrapy_poet/__init__.py
scrapy_poet/_request_fingerprinter.py
scrapy_poet/api.py
scrapy_poet/cache.py
scrapy_poet/commands.py
scrapy_poet/downloader.py
scrapy_poet/downloadermiddlewares.py
scrapy_poet/injection.py
scrapy_poet/injection_errors.py
scrapy_poet/middleware.py
scrapy_poet/page_input_providers.py
scrapy_poet/spidermiddlewares.py
scrapy_poet/utils/__init__.py
scrapy_poet/utils/mockserver.py
scrapy_poet/utils/testing.py
scrapy_poet-0.25.0.dist-info/LICENSE
scrapy_poet-0.25.0.dist-info/METADATA
scrapy_poet-0.25.0.dist-info/WHEEL
scrapy_poet-0.25.0.dist-info/entry_points.txt
scrapy_poet-0.25.0.dist-info/top_level.txt
scrapy_poet-0.25.0.dist-info/RECORD
