Metadata-Version: 2.1
Name: scrapy-poet
Version: 0.25.0
Summary: Page Object pattern for Scrapy
Home-page: https://github.com/scrapinghub/scrapy-poet
Author: Mikhail Korobov
Author-email: kmike84@gmail.com
Classifier: Development Status :: 3 - Alpha
Classifier: Intended Audience :: Developers
Classifier: License :: OSI Approved :: BSD License
Classifier: Natural Language :: English
Classifier: Operating System :: OS Independent
Classifier: Framework :: Scrapy
Classifier: Programming Language :: Python :: 3
Classifier: Programming Language :: Python :: 3.9
Classifier: Programming Language :: Python :: 3.10
Classifier: Programming Language :: Python :: 3.11
Classifier: Programming Language :: Python :: 3.12
Classifier: Programming Language :: Python :: 3.13
Requires-Python: >=3.9
License-File: LICENSE
Requires-Dist: andi>=0.6.0
Requires-Dist: attrs>=21.3.0
Requires-Dist: parsel>=1.5.0
Requires-Dist: scrapy>=2.6.0
Requires-Dist: sqlitedict>=1.5.0
Requires-Dist: time_machine>=2.7.1
Requires-Dist: twisted>=18.9.0
Requires-Dist: url-matcher>=0.2.0
Requires-Dist: web-poet>=0.17.0
